ponstrans/__init__.py
ponstrans/supported_langs.py
ponstrans/translator.py
ponstrans-1.1.1.dist-info/LICENSE.txt
ponstrans-1.1.1.dist-info/METADATA
ponstrans-1.1.1.dist-info/WHEEL
ponstrans-1.1.1.dist-info/top_level.txt
ponstrans-1.1.1.dist-info/RECORD
