Metadata-Version: 2.1
Name: ponstrans
Version: 1.1.1
Summary: Add a short description here!
Home-page: https://github.com/plysytsya/ponstrans
Author: Pavlo Lysytsya
Author-email: pavlo.lysytsya@outfittery.de
License: mit
Project-URL: Documentation, https://github.com/plysytsya/ponstrans
Platform: any
Classifier: Development Status :: 4 - Beta
Classifier: Programming Language :: Python
Requires-Dist: requests (>=2.0.0)
Requires-Dist: beautifulsoup4 (>=4.0.0)
Provides-Extra: testing
Requires-Dist: pytest ; extra == 'testing'
Requires-Dist: pytest-cov ; extra == 'testing'
